{
  "id": "human_body",
  "titleKey": "layer.human.title",
  "descriptionKey": "layer.human.description",
  "colorScale": "human-body",
  "type": "categorical",
  "unit": "%",
  "source": "CRC Handbook of Chemistry and Physics, 97th edition (2016-2017), p. 14-17",
  "notes": [
    "layer.human.note.average",
    "layer.human.note.trace"
  ],
  "inset": {
    "variant": "human-body",
    "titleKey": "layer.human.insetTitle",
    "visual": "human",
    "key": [
      { "labelKey": "scale.essential", "colorVar": "--color-human-essential" },
      { "labelKey": "scale.nonessential", "colorVar": "--color-human-nonessential" }
    ],
    "details": [
      "layer.human.note.average",
      "layer.human.note.trace"
    ]
  },
  "displayValues": {
    "1": "10%",
    "2": "0%",
    "3": "0.00001%",
    "4": "TRACE",
    "5": "0.00003%",
    "6": "22.3%",
    "7": "2.57%",
    "8": "61.4%",
    "9": "0.0037%",
    "10": "0%",
    "11": "0.053%",
    "12": "0.027%",
    "13": "0.00009%",
    "14": "0.0014%",
    "15": "1.11%",
    "16": "0.20%",
    "17": "0.14%",
    "18": "0%",
    "19": "0.047%",
    "20": "1.43%",
    "21": "TRACE",
    "22": "0.00003%",
    "23": "TRACE",
    "24": "0.00002%",
    "25": "0.00002%",
    "26": "0.0060%",
    "27": "TRACE",
    "28": "0.00002%",
    "29": "0.0001%",
    "30": "0.0033%",
    "31": "TRACE",
    "32": "TRACE",
    "33": "0.00001%",
    "34": "0.00002%",
    "35": "0.00037%",
    "36": "0%",
    "37": "0.00097%",
    "38": "0.00046%",
    "39": "TRACE",
    "40": "TRACE",
    "41": "TRACE",
    "42": "TRACE",
    "43": "0%",
    "44": "0%",
    "45": "0%",
    "46": "0%",
    "47": "TRACE",
    "48": "0.00007%",
    "49": "TRACE",
    "50": "0.00003%",
    "51": "TRACE",
    "52": "TRACE",
    "53": "0.00003%",
    "54": "0%",
    "55": "0.00001%",
    "56": "0.00003%",
    "57": "TRACE",
    "58": "0.00006%",
    "59": "0%",
    "60": "0%",
    "61": "0%",
    "62": "TRACE",
    "63": "0%",
    "64": "0%",
    "65": "0%",
    "66": "0%",
    "67": "0%",
    "68": "0%",
    "69": "0%",
    "70": "0%",
    "71": "0%",
    "72": "0%",
    "73": "TRACE",
    "74": "TRACE",
    "75": "0%",
    "76": "0%",
    "77": "0%",
    "78": "0%",
    "79": "TRACE",
    "80": "TRACE",
    "81": "TRACE",
    "82": "0.00017%",
    "83": "TRACE",
    "84": "0%",
    "85": "0%",
    "86": "0%",
    "87": "0%",
    "88": "TRACE",
    "89": "0%",
    "90": "TRACE",
    "91": "0%",
    "92": "TRACE",
    "93": "0%",
    "94": "0%",
    "95": "0%",
    "96": "0%",
    "97": "0%",
    "98": "0%",
    "99": "0%",
    "100": "0%",
    "101": "0%",
    "102": "0%",
    "103": "0%",
    "104": "0%",
    "105": "0%",
    "106": "0%",
    "107": "0%",
    "108": "0%",
    "109": "0%",
    "110": "0%",
    "111": "0%",
    "112": "0%",
    "113": "0%",
    "114": "0%",
    "115": "0%",
    "116": "0%",
    "117": "0%",
    "118": "0%"
  },
  "values": {
    "1": { "category": "essential", "percent": 10 },
    "2": { "category": "zero", "percent": 0 },
    "3": { "category": "nonessential", "percent": 0.00001 },
    "4": { "category": "nonessential", "trace": true },
    "5": { "category": "nonessential", "percent": 0.00003 },
    "6": { "category": "essential", "percent": 22.3 },
    "7": { "category": "essential", "percent": 2.57 },
    "8": { "category": "essential", "percent": 61.4 },
    "9": { "category": "nonessential", "percent": 0.0037 },
    "10": { "category": "zero", "percent": 0 },
    "11": { "category": "essential", "percent": 0.053 },
    "12": { "category": "essential", "percent": 0.027 },
    "13": { "category": "nonessential", "percent": 0.00009 },
    "14": { "category": "nonessential", "percent": 0.0014 },
    "15": { "category": "essential", "percent": 1.11 },
    "16": { "category": "essential", "percent": 0.2 },
    "17": { "category": "essential", "percent": 0.14 },
    "18": { "category": "zero", "percent": 0 },
    "19": { "category": "essential", "percent": 0.047 },
    "20": { "category": "essential", "percent": 1.43 },
    "21": { "category": "nonessential", "trace": true },
    "22": { "category": "nonessential", "percent": 0.00003 },
    "23": { "category": "nonessential", "trace": true },
    "24": { "category": "nonessential", "percent": 0.00002 },
    "25": { "category": "essential", "percent": 0.00002 },
    "26": { "category": "essential", "percent": 0.006 },
    "27": { "category": "essential", "trace": true },
    "28": { "category": "nonessential", "percent": 0.00002 },
    "29": { "category": "essential", "percent": 0.0001 },
    "30": { "category": "essential", "percent": 0.0033 },
    "31": { "category": "nonessential", "trace": true },
    "32": { "category": "nonessential", "trace": true },
    "33": { "category": "nonessential", "percent": 0.00001 },
    "34": { "category": "essential", "percent": 0.00002 },
    "35": { "category": "nonessential", "percent": 0.00037 },
    "36": { "category": "zero", "percent": 0 },
    "37": { "category": "nonessential", "percent": 0.00097 },
    "38": { "category": "nonessential", "percent": 0.00046 },
    "39": { "category": "nonessential", "trace": true },
    "40": { "category": "nonessential", "trace": true },
    "41": { "category": "nonessential", "trace": true },
    "42": { "category": "essential", "trace": true },
    "43": { "category": "zero", "percent": 0 },
    "44": { "category": "zero", "percent": 0 },
    "45": { "category": "zero", "percent": 0 },
    "46": { "category": "zero", "percent": 0 },
    "47": { "category": "nonessential", "trace": true },
    "48": { "category": "nonessential", "percent": 0.00007 },
    "49": { "category": "nonessential", "trace": true },
    "50": { "category": "nonessential", "percent": 0.00003 },
    "51": { "category": "nonessential", "trace": true },
    "52": { "category": "nonessential", "trace": true },
    "53": { "category": "essential", "percent": 0.00003 },
    "54": { "category": "zero", "percent": 0 },
    "55": { "category": "nonessential", "percent": 0.00001 },
    "56": { "category": "nonessential", "percent": 0.00003 },
    "57": { "category": "nonessential", "trace": true },
    "58": { "category": "nonessential", "percent": 0.00006 },
    "59": { "category": "zero", "percent": 0 },
    "60": { "category": "zero", "percent": 0 },
    "61": { "category": "zero", "percent": 0 },
    "62": { "category": "nonessential", "trace": true },
    "63": { "category": "zero", "percent": 0 },
    "64": { "category": "zero", "percent": 0 },
    "65": { "category": "zero", "percent": 0 },
    "66": { "category": "zero", "percent": 0 },
    "67": { "category": "zero", "percent": 0 },
    "68": { "category": "zero", "percent": 0 },
    "69": { "category": "zero", "percent": 0 },
    "70": { "category": "zero", "percent": 0 },
    "71": { "category": "zero", "percent": 0 },
    "72": { "category": "zero", "percent": 0 },
    "73": { "category": "nonessential", "trace": true },
    "74": { "category": "nonessential", "trace": true },
    "75": { "category": "zero", "percent": 0 },
    "76": { "category": "zero", "percent": 0 },
    "77": { "category": "zero", "percent": 0 },
    "78": { "category": "zero", "percent": 0 },
    "79": { "category": "nonessential", "trace": true },
    "80": { "category": "nonessential", "trace": true },
    "81": { "category": "nonessential", "trace": true },
    "82": { "category": "nonessential", "percent": 0.00017 },
    "83": { "category": "nonessential", "trace": true },
    "84": { "category": "zero", "percent": 0 },
    "85": { "category": "zero", "percent": 0 },
    "86": { "category": "zero", "percent": 0 },
    "87": { "category": "zero", "percent": 0 },
    "88": { "category": "nonessential", "trace": true },
    "89": { "category": "zero", "percent": 0 },
    "90": { "category": "nonessential", "trace": true },
    "91": { "category": "zero", "percent": 0 },
    "92": { "category": "nonessential", "trace": true },
    "93": { "category": "zero", "percent": 0 },
    "94": { "category": "zero", "percent": 0 },
    "95": { "category": "zero", "percent": 0 },
    "96": { "category": "zero", "percent": 0 },
    "97": { "category": "zero", "percent": 0 },
    "98": { "category": "zero", "percent": 0 },
    "99": { "category": "zero", "percent": 0 },
    "100": { "category": "zero", "percent": 0 },
    "101": { "category": "zero", "percent": 0 },
    "102": { "category": "zero", "percent": 0 },
    "103": { "category": "zero", "percent": 0 },
    "104": { "category": "zero", "percent": 0 },
    "105": { "category": "zero", "percent": 0 },
    "106": { "category": "zero", "percent": 0 },
    "107": { "category": "zero", "percent": 0 },
    "108": { "category": "zero", "percent": 0 },
    "109": { "category": "zero", "percent": 0 },
    "110": { "category": "zero", "percent": 0 },
    "111": { "category": "zero", "percent": 0 },
    "112": { "category": "zero", "percent": 0 },
    "113": { "category": "zero", "percent": 0 },
    "114": { "category": "zero", "percent": 0 },
    "115": { "category": "zero", "percent": 0 },
    "116": { "category": "zero", "percent": 0 },
    "117": { "category": "zero", "percent": 0 },
    "118": { "category": "zero", "percent": 0 }
  }
}
